g42so/__init__.py
g42so/detect_compiler.py
g42so/detector_wrapper.cc.in
g42so/find_classes.py
g42so/generate_library.py
g42so/main.py
g42so/pga_wrapper.cc.in
g42so/version.cc
g42so-0.3.0.dist-info/LICENSE
g42so-0.3.0.dist-info/METADATA
g42so-0.3.0.dist-info/WHEEL
g42so-0.3.0.dist-info/entry_points.txt
g42so-0.3.0.dist-info/top_level.txt
g42so-0.3.0.dist-info/RECORD
