Metadata-Version: 2.1
Name: g42so
Version: 0.3.0
Summary: A tool to convert Geant4 geometries into shared libraries
Home-page: https://github.com/arekfu/g42so
Author: Davide Mancusi
Author-email: davide.mancusi@cea.fr
License: UNKNOWN
Platform: UNKNOWN
Classifier: Programming Language :: Python :: 2
Classifier: Programming Language :: Python :: 3
Classifier: Development Status :: 4 - Beta
Classifier: Environment :: Console
Classifier: License :: OSI Approved :: MIT License
Classifier: Operating System :: POSIX :: Linux
Classifier: Topic :: Scientific/Engineering :: Physics
Requires-Python: >=2.6, <4
